pyiceberg_core/__init__.py
pyiceberg_core/pyiceberg_core_rust.abi3.so
pyiceberg_core-0.8.0.dist-info/METADATA
pyiceberg_core-0.8.0.dist-info/WHEEL
pyiceberg_core-0.8.0.dist-info/licenses/LICENSE
pyiceberg_core-0.8.0.dist-info/licenses/NOTICE
pyiceberg_core-0.8.0.dist-info/RECORD
